bilateralshapley/__init__.py
bilateralshapley/bilateralshapley.py
bilateralshapley-0.0.3.dist-info/LICENSE
bilateralshapley-0.0.3.dist-info/METADATA
bilateralshapley-0.0.3.dist-info/WHEEL
bilateralshapley-0.0.3.dist-info/top_level.txt
bilateralshapley-0.0.3.dist-info/RECORD
