Metadata-Version: 2.1
Name: bilateralshapley
Version: 0.0.3
Summary: Employs Bilateral Shapley Value from coalition game theory as a tool to assess agent coalition formation
Home-page: https://github.com/tpike3/bilateralshapley
Author: Tom Pike
Author-email: tpike3@gmu.edu
License: UNKNOWN
Keywords: agent based modeling model ABM simulation multi-agent coaltion game theory
Platform: UNKNOWN
Classifier: Topic :: Scientific/Engineering
Classifier: Topic :: Scientific/Engineering :: Artificial Life
Classifier: Topic :: Scientific/Engineering :: Artificial Intelligence
Classifier: Intended Audience :: Science/Research
Classifier: Programming Language :: Python :: 3 :: Only
Classifier: License :: OSI Approved :: MIT License
Classifier: Operating System :: OS Independent
Classifier: Development Status :: 2 - Pre-Alpha
Classifier: Natural Language :: English
Requires-Dist: networkx
